matform/__init__.py
matform/meta_singleton.py
matform/stdRV.py
matform/structure_to_geometry.py
matform/subprocess.py
matform/array/__init__.py
matform/array/array_dict_data.py
matform/array/array_to_image.py
matform/array/axis_rotation.py
matform/array/labeledTensor.py
matform/array/text_matrix_expression.py
matform/database/__init__.py
matform/database/db.py
matform/database/item.py
matform/database/table.py
matform-0.1.18.dist-info/licenses/LICENSE
matform-0.1.18.dist-info/METADATA
matform-0.1.18.dist-info/WHEEL
matform-0.1.18.dist-info/top_level.txt
matform-0.1.18.dist-info/RECORD
